{
  "content_scale": 1.0,
  "armature_data": [
    {
      "strVersion": "1.6.0.0",
      "version": 1.6,
      "name": "shansuokuang",
      "bone_data": [
        {
          "name": "Layer1_Copy2_Copy3",
          "parent": "",
          "dI": 0,
          "x": 0.0,
          "y": 0.0,
          "z": 4,
          "cX": 1.0,
          "cY": 1.0,
          "kX": 0.0,
          "kY": 0.0,
          "arrow_x": 0.0,
          "arrow_y": 0.0,
          "effectbyskeleton": false,
          "bl": 0,
          "display_data": [
            {
              "name": "xxqp_jx_02.png",
              "displayType": 0,
              "skin_data": [
                {
                  "x": 0.0,
                  "y": 0.0,
                  "cX": 1.0,
                  "cY": 1.0,
                  "kX": 0.0,
                  "kY": 0.0
                }
              ]
            }
          ]
        },
        {
          "name": "Layer1_Copy2",
          "parent": "",
          "dI": 0,
          "x": 0.0,
          "y": 0.0,
          "z": 3,
          "cX": 1.0,
          "cY": 1.0,
          "kX": 0.0,
          "kY": 0.0,
          "arrow_x": 0.0,
          "arrow_y": 0.0,
          "effectbyskeleton": false,
          "bl": 0,
          "display_data": [
            {
              "name": "xxqp_jx_02.png",
              "displayType": 0,
              "skin_data": [
                {
                  "x": 0.0,
                  "y": 0.0,
                  "cX": 1.0,
                  "cY": 1.0,
                  "kX": 0.0,
                  "kY": 0.0
                }
              ]
            }
          ]
        },
        {
          "name": "Layer1",
          "parent": "",
          "dI": 0,
          "x": 0.0,
          "y": 0.0,
          "z": 2,
          "cX": 1.0,
          "cY": 1.0,
          "kX": 0.0,
          "kY": 0.0,
          "arrow_x": 0.0,
          "arrow_y": 0.0,
          "effectbyskeleton": false,
          "bl": 0,
          "display_data": [
            {
              "name": "xxqp_jx_02.png",
              "displayType": 0,
              "skin_data": [
                {
                  "x": 0.0,
                  "y": 0.0,
                  "cX": 1.0,
                  "cY": 1.0,
                  "kX": 0.0,
                  "kY": 0.0
                }
              ]
            }
          ]
        },
        {
          "name": "Layer5",
          "parent": "",
          "dI": 0,
          "x": 590.29400634765625,
          "y": -137.73651123046875,
          "z": 1,
          "cX": 1.0,
          "cY": 1.0,
          "kX": 0.0,
          "kY": 0.0,
          "arrow_x": 0.0,
          "arrow_y": 0.0,
          "effectbyskeleton": false,
          "bl": 0,
          "display_data": [
            {
              "name": "22.png",
              "displayType": 0,
              "skin_data": [
                {
                  "x": 0.0,
                  "y": 0.0,
                  "cX": 1.0,
                  "cY": 1.0,
                  "kX": 0.0,
                  "kY": 0.0
                }
              ]
            }
          ]
        }
      ]
    }
  ],
  "animation_data": [
    {
      "name": "shansuokuang",
      "mov_data": [
        {
          "name": "Animation1",
          "dr": 166,
          "lp": true,
          "to": 0,
          "drTW": 0,
          "twE": 0,
          "sc": 1.0,
          "mov_bone_data": [
            {
              "name": "Layer1_Copy2_Copy3",
              "dl": 0.0,
              "frame_data": [
                {
                  "dI": 0,
                  "x": 0.0,
                  "y": 0.0,
                  "z": 0,
                  "cX": 1.0,
                  "cY": 1.0,
                  "kX": 0.0,
                  "kY": 0.0,
                  "fi": 105,
                  "twE": 0,
                  "tweenFrame": true,
                  "color": {
                    "a": 0,
                    "r": 255,
                    "g": 255,
                    "b": 255
                  },
                  "bd_src": 1,
                  "bd_dst": 771
                },
                {
                  "dI": 0,
                  "x": 0.0,
                  "y": 0.0,
                  "z": 0,
                  "cX": 1.3,
                  "cY": 1.3,
                  "kX": 0.0,
                  "kY": 0.0,
                  "fi": 136,
                  "twE": 0,
                  "tweenFrame": true,
                  "color": {
                    "a": 180,
                    "r": 255,
                    "g": 255,
                    "b": 255
                  },
                  "bd_src": 1,
                  "bd_dst": 771
                },
                {
                  "dI": 0,
                  "x": 0.0,
                  "y": 0.0,
                  "z": 0,
                  "cX": 1.3,
                  "cY": 1.3,
                  "kX": 0.0,
                  "kY": 0.0,
                  "fi": 165,
                  "twE": 0,
                  "tweenFrame": true,
                  "color": {
                    "a": 0,
                    "r": 255,
                    "g": 255,
                    "b": 255
                  },
                  "bd_src": 1,
                  "bd_dst": 771
                }
              ]
            },
            {
              "name": "Layer1_Copy2",
              "dl": 0.0,
              "frame_data": [
                {
                  "dI": 0,
                  "x": 0.0,
                  "y": 0.0,
                  "z": 0,
                  "cX": 1.0,
                  "cY": 1.0,
                  "kX": 0.0,
                  "kY": 0.0,
                  "fi": 90,
                  "twE": 0,
                  "tweenFrame": true,
                  "color": {
                    "a": 0,
                    "r": 255,
                    "g": 255,
                    "b": 255
                  },
                  "bd_src": 1,
                  "bd_dst": 771
                },
                {
                  "dI": 0,
                  "x": 0.0,
                  "y": 0.0,
                  "z": 0,
                  "cX": 1.3,
                  "cY": 1.3,
                  "kX": 0.0,
                  "kY": 0.0,
                  "fi": 105,
                  "twE": 0,
                  "tweenFrame": true,
                  "color": {
                    "a": 155,
                    "r": 255,
                    "g": 255,
                    "b": 255
                  },
                  "bd_src": 1,
                  "bd_dst": 771
                },
                {
                  "dI": 0,
                  "x": 0.0,
                  "y": 0.0,
                  "z": 0,
                  "cX": 1.3,
                  "cY": 1.3,
                  "kX": 0.0,
                  "kY": 0.0,
                  "fi": 130,
                  "twE": 0,
                  "tweenFrame": true,
                  "color": {
                    "a": 48,
                    "r": 255,
                    "g": 255,
                    "b": 255
                  },
                  "bd_src": 1,
                  "bd_dst": 771
                },
                {
                  "dI": 0,
                  "x": 0.0,
                  "y": 0.0,
                  "z": 0,
                  "cX": 1.3,
                  "cY": 1.3,
                  "kX": 0.0,
                  "kY": 0.0,
                  "fi": 155,
                  "twE": 0,
                  "tweenFrame": true,
                  "color": {
                    "a": 0,
                    "r": 255,
                    "g": 255,
                    "b": 255
                  },
                  "bd_src": 1,
                  "bd_dst": 771
                }
              ]
            },
            {
              "name": "Layer1",
              "dl": 0.0,
              "frame_data": [
                {
                  "dI": 0,
                  "x": 0.0,
                  "y": 0.0,
                  "z": 0,
                  "cX": 1.0,
                  "cY": 1.0,
                  "kX": 0.0,
                  "kY": 0.0,
                  "fi": 0,
                  "twE": 0,
                  "tweenFrame": true,
                  "color": {
                    "a": 255,
                    "r": 255,
                    "g": 255,
                    "b": 255
                  },
                  "bd_src": 1,
                  "bd_dst": 771
                },
                {
                  "dI": 0,
                  "x": 0.0,
                  "y": 0.0,
                  "z": 0,
                  "cX": 1.0,
                  "cY": 1.0,
                  "kX": 0.0,
                  "kY": 0.0,
                  "fi": 15,
                  "twE": 0,
                  "tweenFrame": true,
                  "color": {
                    "a": 50,
                    "r": 255,
                    "g": 255,
                    "b": 255
                  },
                  "bd_src": 1,
                  "bd_dst": 771
                },
                {
                  "dI": 0,
                  "x": 0.0,
                  "y": 0.0,
                  "z": 0,
                  "cX": 1.0,
                  "cY": 1.0,
                  "kX": 0.0,
                  "kY": 0.0,
                  "fi": 30,
                  "twE": 0,
                  "tweenFrame": true,
                  "color": {
                    "a": 255,
                    "r": 255,
                    "g": 255,
                    "b": 255
                  },
                  "bd_src": 1,
                  "bd_dst": 771
                },
                {
                  "dI": 0,
                  "x": 0.0,
                  "y": 0.0,
                  "z": 0,
                  "cX": 1.0,
                  "cY": 1.0,
                  "kX": 0.0,
                  "kY": 0.0,
                  "fi": 45,
                  "twE": 0,
                  "tweenFrame": true,
                  "color": {
                    "a": 50,
                    "r": 255,
                    "g": 255,
                    "b": 255
                  },
                  "bd_src": 1,
                  "bd_dst": 771
                },
                {
                  "dI": 0,
                  "x": 0.0,
                  "y": 0.0,
                  "z": 0,
                  "cX": 1.0,
                  "cY": 1.0,
                  "kX": 0.0,
                  "kY": 0.0,
                  "fi": 46,
                  "twE": 0,
                  "tweenFrame": true,
                  "color": {
                    "a": 50,
                    "r": 255,
                    "g": 255,
                    "b": 255
                  },
                  "bd_src": 1,
                  "bd_dst": 771
                },
                {
                  "dI": 0,
                  "x": 0.0,
                  "y": 0.0,
                  "z": 0,
                  "cX": 1.0,
                  "cY": 1.0,
                  "kX": 0.0,
                  "kY": 0.0,
                  "fi": 48,
                  "twE": 0,
                  "tweenFrame": true,
                  "color": {
                    "a": 50,
                    "r": 255,
                    "g": 255,
                    "b": 255
                  },
                  "bd_src": 1,
                  "bd_dst": 771
                },
                {
                  "dI": 0,
                  "x": 0.0,
                  "y": 0.0,
                  "z": 0,
                  "cX": 1.0,
                  "cY": 1.0,
                  "kX": 0.0,
                  "kY": 0.0,
                  "fi": 49,
                  "twE": 0,
                  "tweenFrame": true,
                  "color": {
                    "a": 255,
                    "r": 255,
                    "g": 255,
                    "b": 255
                  },
                  "bd_src": 1,
                  "bd_dst": 771
                },
                {
                  "dI": 0,
                  "x": 0.0,
                  "y": 0.0,
                  "z": 0,
                  "cX": 1.0,
                  "cY": 1.0,
                  "kX": 0.0,
                  "kY": 0.0,
                  "fi": 51,
                  "twE": 0,
                  "tweenFrame": true,
                  "color": {
                    "a": 255,
                    "r": 255,
                    "g": 255,
                    "b": 255
                  },
                  "bd_src": 1,
                  "bd_dst": 771
                },
                {
                  "dI": 0,
                  "x": 0.0,
                  "y": 0.0,
                  "z": 0,
                  "cX": 1.0,
                  "cY": 1.0,
                  "kX": 0.0,
                  "kY": 0.0,
                  "fi": 52,
                  "twE": 0,
                  "tweenFrame": true,
                  "color": {
                    "a": 50,
                    "r": 255,
                    "g": 255,
                    "b": 255
                  },
                  "bd_src": 1,
                  "bd_dst": 771
                },
                {
                  "dI": 0,
                  "x": 0.0,
                  "y": 0.0,
                  "z": 0,
                  "cX": 1.0,
                  "cY": 1.0,
                  "kX": 0.0,
                  "kY": 0.0,
                  "fi": 54,
                  "twE": 0,
                  "tweenFrame": true,
                  "color": {
                    "a": 50,
                    "r": 255,
                    "g": 255,
                    "b": 255
                  },
                  "bd_src": 1,
                  "bd_dst": 771
                },
                {
                  "dI": 0,
                  "x": 0.0,
                  "y": 0.0,
                  "z": 0,
                  "cX": 1.0,
                  "cY": 1.0,
                  "kX": 0.0,
                  "kY": 0.0,
                  "fi": 55,
                  "twE": 0,
                  "tweenFrame": true,
                  "color": {
                    "a": 255,
                    "r": 255,
                    "g": 255,
                    "b": 255
                  },
                  "bd_src": 1,
                  "bd_dst": 771
                },
                {
                  "dI": 0,
                  "x": 0.0,
                  "y": 0.0,
                  "z": 0,
                  "cX": 1.0,
                  "cY": 1.0,
                  "kX": 0.0,
                  "kY": 0.0,
                  "fi": 57,
                  "twE": 0,
                  "tweenFrame": true,
                  "color": {
                    "a": 255,
                    "r": 255,
                    "g": 255,
                    "b": 255
                  },
                  "bd_src": 1,
                  "bd_dst": 771
                },
                {
                  "dI": 0,
                  "x": 0.0,
                  "y": 0.0,
                  "z": 0,
                  "cX": 1.0,
                  "cY": 1.0,
                  "kX": 0.0,
                  "kY": 0.0,
                  "fi": 58,
                  "twE": 0,
                  "tweenFrame": true,
                  "color": {
                    "a": 50,
                    "r": 255,
                    "g": 255,
                    "b": 255
                  },
                  "bd_src": 1,
                  "bd_dst": 771
                },
                {
                  "dI": 0,
                  "x": 0.0,
                  "y": 0.0,
                  "z": 0,
                  "cX": 1.0,
                  "cY": 1.0,
                  "kX": 0.0,
                  "kY": 0.0,
                  "fi": 60,
                  "twE": 0,
                  "tweenFrame": true,
                  "color": {
                    "a": 50,
                    "r": 255,
                    "g": 255,
                    "b": 255
                  },
                  "bd_src": 1,
                  "bd_dst": 771
                },
                {
                  "dI": 0,
                  "x": 0.0,
                  "y": 0.0,
                  "z": 0,
                  "cX": 1.0,
                  "cY": 1.0,
                  "kX": 0.0,
                  "kY": 0.0,
                  "fi": 61,
                  "twE": 0,
                  "tweenFrame": true,
                  "color": {
                    "a": 255,
                    "r": 255,
                    "g": 255,
                    "b": 255
                  },
                  "bd_src": 1,
                  "bd_dst": 771
                },
                {
                  "dI": 0,
                  "x": 0.0,
                  "y": 0.0,
                  "z": 0,
                  "cX": 1.0,
                  "cY": 1.0,
                  "kX": 0.0,
                  "kY": 0.0,
                  "fi": 63,
                  "twE": 0,
                  "tweenFrame": true,
                  "color": {
                    "a": 255,
                    "r": 255,
                    "g": 255,
                    "b": 255
                  },
                  "bd_src": 1,
                  "bd_dst": 771
                },
                {
                  "dI": 0,
                  "x": 0.0,
                  "y": 0.0,
                  "z": 0,
                  "cX": 1.0,
                  "cY": 1.0,
                  "kX": 0.0,
                  "kY": 0.0,
                  "fi": 64,
                  "twE": 0,
                  "tweenFrame": true,
                  "color": {
                    "a": 50,
                    "r": 255,
                    "g": 255,
                    "b": 255
                  },
                  "bd_src": 1,
                  "bd_dst": 771
                },
                {
                  "dI": 0,
                  "x": 0.0,
                  "y": 0.0,
                  "z": 0,
                  "cX": 1.0,
                  "cY": 1.0,
                  "kX": 0.0,
                  "kY": 0.0,
                  "fi": 66,
                  "twE": 0,
                  "tweenFrame": true,
                  "color": {
                    "a": 50,
                    "r": 255,
                    "g": 255,
                    "b": 255
                  },
                  "bd_src": 1,
                  "bd_dst": 771
                },
                {
                  "dI": 0,
                  "x": 0.0,
                  "y": 0.0,
                  "z": 0,
                  "cX": 1.0,
                  "cY": 1.0,
                  "kX": 0.0,
                  "kY": 0.0,
                  "fi": 67,
                  "twE": 0,
                  "tweenFrame": true,
                  "color": {
                    "a": 255,
                    "r": 255,
                    "g": 255,
                    "b": 255
                  },
                  "bd_src": 1,
                  "bd_dst": 771
                },
                {
                  "dI": 0,
                  "x": 0.0,
                  "y": 0.0,
                  "z": 0,
                  "cX": 1.0,
                  "cY": 1.0,
                  "kX": 0.0,
                  "kY": 0.0,
                  "fi": 69,
                  "twE": 0,
                  "tweenFrame": true,
                  "color": {
                    "a": 255,
                    "r": 255,
                    "g": 255,
                    "b": 255
                  },
                  "bd_src": 1,
                  "bd_dst": 771
                },
                {
                  "dI": 0,
                  "x": 0.0,
                  "y": 0.0,
                  "z": 0,
                  "cX": 1.0,
                  "cY": 1.0,
                  "kX": 0.0,
                  "kY": 0.0,
                  "fi": 70,
                  "twE": 0,
                  "tweenFrame": true,
                  "color": {
                    "a": 50,
                    "r": 255,
                    "g": 255,
                    "b": 255
                  },
                  "bd_src": 1,
                  "bd_dst": 771
                },
                {
                  "dI": 0,
                  "x": 0.0,
                  "y": 0.0,
                  "z": 0,
                  "cX": 1.0,
                  "cY": 1.0,
                  "kX": 0.0,
                  "kY": 0.0,
                  "fi": 72,
                  "twE": 0,
                  "tweenFrame": true,
                  "color": {
                    "a": 50,
                    "r": 255,
                    "g": 255,
                    "b": 255
                  },
                  "bd_src": 1,
                  "bd_dst": 771
                },
                {
                  "dI": 0,
                  "x": 0.0,
                  "y": 0.0,
                  "z": 0,
                  "cX": 1.0,
                  "cY": 1.0,
                  "kX": 0.0,
                  "kY": 0.0,
                  "fi": 73,
                  "twE": 0,
                  "tweenFrame": true,
                  "color": {
                    "a": 255,
                    "r": 255,
                    "g": 255,
                    "b": 255
                  },
                  "bd_src": 1,
                  "bd_dst": 771
                },
                {
                  "dI": 0,
                  "x": 0.0,
                  "y": 0.0,
                  "z": 0,
                  "cX": 1.0,
                  "cY": 1.0,
                  "kX": 0.0,
                  "kY": 0.0,
                  "fi": 75,
                  "twE": 0,
                  "tweenFrame": true,
                  "color": {
                    "a": 255,
                    "r": 255,
                    "g": 255,
                    "b": 255
                  },
                  "bd_src": 1,
                  "bd_dst": 771
                },
                {
                  "dI": 0,
                  "x": 0.0,
                  "y": 0.0,
                  "z": 0,
                  "cX": 1.0,
                  "cY": 1.0,
                  "kX": 0.0,
                  "kY": 0.0,
                  "fi": 76,
                  "twE": 0,
                  "tweenFrame": true,
                  "color": {
                    "a": 50,
                    "r": 255,
                    "g": 255,
                    "b": 255
                  },
                  "bd_src": 1,
                  "bd_dst": 771
                },
                {
                  "dI": 0,
                  "x": 0.0,
                  "y": 0.0,
                  "z": 0,
                  "cX": 1.0,
                  "cY": 1.0,
                  "kX": 0.0,
                  "kY": 0.0,
                  "fi": 78,
                  "twE": 0,
                  "tweenFrame": true,
                  "color": {
                    "a": 50,
                    "r": 255,
                    "g": 255,
                    "b": 255
                  },
                  "bd_src": 1,
                  "bd_dst": 771
                },
                {
                  "dI": 0,
                  "x": 0.0,
                  "y": 0.0,
                  "z": 0,
                  "cX": 1.0,
                  "cY": 1.0,
                  "kX": 0.0,
                  "kY": 0.0,
                  "fi": 79,
                  "twE": 0,
                  "tweenFrame": true,
                  "color": {
                    "a": 255,
                    "r": 255,
                    "g": 255,
                    "b": 255
                  },
                  "bd_src": 1,
                  "bd_dst": 771
                },
                {
                  "dI": 0,
                  "x": 0.0,
                  "y": 0.0,
                  "z": 0,
                  "cX": 1.0,
                  "cY": 1.0,
                  "kX": 0.0,
                  "kY": 0.0,
                  "fi": 81,
                  "twE": 0,
                  "tweenFrame": true,
                  "color": {
                    "a": 255,
                    "r": 255,
                    "g": 255,
                    "b": 255
                  },
                  "bd_src": 1,
                  "bd_dst": 771
                },
                {
                  "dI": 0,
                  "x": 0.0,
                  "y": 0.0,
                  "z": 0,
                  "cX": 1.0,
                  "cY": 1.0,
                  "kX": 0.0,
                  "kY": 0.0,
                  "fi": 82,
                  "twE": 0,
                  "tweenFrame": true,
                  "color": {
                    "a": 50,
                    "r": 255,
                    "g": 255,
                    "b": 255
                  },
                  "bd_src": 1,
                  "bd_dst": 771
                },
                {
                  "dI": 0,
                  "x": 0.0,
                  "y": 0.0,
                  "z": 0,
                  "cX": 1.0,
                  "cY": 1.0,
                  "kX": 0.0,
                  "kY": 0.0,
                  "fi": 84,
                  "twE": 0,
                  "tweenFrame": true,
                  "color": {
                    "a": 50,
                    "r": 255,
                    "g": 255,
                    "b": 255
                  },
                  "bd_src": 1,
                  "bd_dst": 771
                },
                {
                  "dI": 0,
                  "x": 0.0,
                  "y": 0.0,
                  "z": 0,
                  "cX": 1.0,
                  "cY": 1.0,
                  "kX": 0.0,
                  "kY": 0.0,
                  "fi": 85,
                  "twE": 0,
                  "tweenFrame": true,
                  "color": {
                    "a": 255,
                    "r": 255,
                    "g": 255,
                    "b": 255
                  },
                  "bd_src": 1,
                  "bd_dst": 771
                },
                {
                  "dI": 0,
                  "x": 0.0,
                  "y": 0.0,
                  "z": 0,
                  "cX": 1.0,
                  "cY": 1.0,
                  "kX": 0.0,
                  "kY": 0.0,
                  "fi": 90,
                  "twE": 0,
                  "tweenFrame": true,
                  "color": {
                    "a": 255,
                    "r": 255,
                    "g": 255,
                    "b": 255
                  },
                  "bd_src": 1,
                  "bd_dst": 771
                }
              ]
            },
            {
              "name": "Layer5",
              "dl": 0.0,
              "frame_data": [
                {
                  "dI": 0,
                  "x": 0.0,
                  "y": 0.0,
                  "z": 0,
                  "cX": 1.0,
                  "cY": 1.0,
                  "kX": 0.0,
                  "kY": 0.0,
                  "fi": 0,
                  "twE": 0,
                  "tweenFrame": true,
                  "bd_src": 1,
                  "bd_dst": 771
                }
              ]
            }
          ]
        }
      ]
    }
  ],
  "texture_data": [
    {
      "name": "xxqp_jx_02",
      "width": 87.0,
      "height": 87.0,
      "pX": 0.5,
      "pY": 0.5,
      "plistFile": ""
    },
    {
      "name": "22",
      "width": 1334.0,
      "height": 750.0,
      "pX": 0.5,
      "pY": 0.5,
      "plistFile": ""
    }
  ],
  "config_file_path": [],
  "config_png_path": []
}